CoursesHacking/__init__.py
CoursesHacking/courses.py
CoursesHacking/utility.py
CoursesHacking-0.1.1.dist-info/METADATA
CoursesHacking-0.1.1.dist-info/WHEEL
CoursesHacking-0.1.1.dist-info/top_level.txt
CoursesHacking-0.1.1.dist-info/RECORD
