Metadata-Version: 2.1
Name: CoursesHacking
Version: 0.1.1
Summary: UNa biblioteca de los cursos para los principales certificados para un hacker ethico
Home-page: https://hack4u.io
Author: Jonathan Jesus
